aiebash/__init__.py
aiebash/__main__.py
aiebash/arguments.py
aiebash/config_manager.py
aiebash/config_menu.py
aiebash/default_config.yaml
aiebash/error_messages.py
aiebash/formatter_text.py
aiebash/i18n.py
aiebash/llm_client.py
aiebash/logger.py
aiebash/script_executor.py
aiebash/settings_overview.py
aiebash/sys_info.py
aiebash/locales/__init__.py
aiebash/locales/ru.json
aiebash/locales/template_locale.json
aiebash/tests/conftest.py
aiebash/tests/test_main.py
aiebash/tests/test_openai_client.py
ai_ebash-0.5.26.dist-info/METADATA
ai_ebash-0.5.26.dist-info/WHEEL
ai_ebash-0.5.26.dist-info/entry_points.txt
ai_ebash-0.5.26.dist-info/top_level.txt
ai_ebash-0.5.26.dist-info/RECORD
