Metadata-Version: 2.4
Name: ai-ebash
Version: 0.5.26
Summary: Console utility for integrating artificial intelligence into a Linux terminal.
Author: Andrey Bochkarev
Author-email: andrey.bch.1976@gmail.com
License: MIT
Requires-Python: >=3.11
Requires-Dist: certifi==2025.8.3
Requires-Dist: charset-normalizer==3.4.3
Requires-Dist: idna==3.10
Requires-Dist: markdown-it-py==3.0.0
Requires-Dist: mdurl==0.1.2
Requires-Dist: platformdirs==4.4.0
Requires-Dist: Pygments==2.19.2
Requires-Dist: requests==2.32.5
Requires-Dist: rich==14.1.0
Requires-Dist: urllib3==2.5.0
Requires-Dist: openai==1.108.0
Requires-Dist: PyYAML==6.0.2
Requires-Dist: inquirer==3.4.0
Requires-Dist: prompt-toolkit==3.0.52
